LICENSE
MANIFEST.in
README.md
setup.py
bin/rlzrun
rlzero/Animation.py
rlzero/Gamepad.py
rlzero/Keyboard.py
rlzero/Model.py
rlzero/Mouse.py
rlzero/Sound.py
rlzero/Sprite.py
rlzero/__init__.py
rlzero/__main__.py
rlzero/basic_lighting.fs
rlzero/basic_lighting.vs
rlzero/common.py
rlzero/globals.py
rlzero/rlights.py
rlzero/rlzero.iml
rlzero/runner.py
rlzero/shape.py
rlzero/util.py
rlzero.egg-info/PKG-INFO
rlzero.egg-info/SOURCES.txt
rlzero.egg-info/dependency_links.txt
rlzero.egg-info/requires.txt
rlzero.egg-info/top_level.txt
rlzero/data/images/alien.png
rlzero/data/images/alien_hurt.png
rlzero/data/models/Wizard.glb
rlzero/data/sounds/eep.wav