Metadata-Version: 2.1
Name: rlzero
Version: 0.4.2
Summary: Pygame Zero like API to teach 3d games programming based on Raylib
Home-page: https://github.com/electronstudio/rlzero
Author: Electron Studio
Author-email: github@electronstudio.co.uk
License: LGPLv3+
Platform: UNKNOWN
Classifier: License :: OSI Approved :: GNU Lesser General Public License v3 or later (LGPLv3+)
Classifier: Programming Language :: Python :: 3
Classifier: Programming Language :: Python :: 3.7
Classifier: Programming Language :: Python :: 3.8
Classifier: Programming Language :: Python :: 3.9
Classifier: Programming Language :: Python :: 3.10
License-File: LICENSE
